pyappkit/__init__.py
pyappkit/app_config.py
pyappkit/common_utils.py
pyappkit/daemon/__init__.py
pyappkit/daemon/daemon.py
pyappkit/daemon/mordor.py
pyappkit/daemon/tools.py
pyappkit/daemon/worker.py
pyappkit/rabbitmq/__init__.py
pyappkit/rabbitmq/main.py
pyappkit-0.0.21.dist-info/LICENSE
pyappkit-0.0.21.dist-info/METADATA
pyappkit-0.0.21.dist-info/WHEEL
pyappkit-0.0.21.dist-info/entry_points.txt
pyappkit-0.0.21.dist-info/top_level.txt
pyappkit-0.0.21.dist-info/RECORD
