Metadata-Version: 2.1
Name: pyappkit
Version: 0.0.21
Summary: Python Application Kit
Home-page: https://github.com/stonezhong/pyappkit
Author: Stone Zhong
Author-email: stonezhong@hotmail.com
License: MIT
Classifier: License :: OSI Approved :: MIT License
Classifier: Programming Language :: Python :: 3
License-File: LICENSE
Requires-Dist: jinja2
Requires-Dist: PyYAML
Requires-Dist: pydantic
